llm_inferencer/__init__.py
llm_inferencer/model_list.yaml
llm_inferencer/model_list_empty.yaml
llm_inferencer/register.py
llm_inferencer/server_gateway.py
llm_inferencer/utils.py
llm_inferencer/local/__init__.py
llm_inferencer/local/reader/__init__.py
llm_inferencer/local/reader/vllm_predict.py
llm_inferencer/local/reader/vllm_predict_base.py
llm_inferencer/local/reader/vllm_use_example.py
llm_inferencer/local/server/__init__.py
llm_inferencer/local/server/redis_server.py
llm_inferencer/local/server/single_model_server.py
llm_inferencer/remote/__init__.py
llm_inferencer/remote/api_predict.py
llm_inferencer/remote/test.py
llm_inferencer-0.0.22.dist-info/METADATA
llm_inferencer-0.0.22.dist-info/WHEEL
llm_inferencer-0.0.22.dist-info/entry_points.txt
llm_inferencer-0.0.22.dist-info/top_level.txt
llm_inferencer-0.0.22.dist-info/RECORD
